Metadata-Version: 1.0
Name: jinjath
Version: 1.0.0
Summary: Helper classes for working with Jinja templates
Home-page: https://github.com/wtsi-hgi/jinjath
Author: UNKNOWN
Author-email: UNKNOWN
License: GPL3
Platform: UNKNOWN
